primes/__init__.py
primes/primes.py
primes/primes_alternate_ways.py
fast_prime_numbers-0.0.3.dist-info/LICENSE
fast_prime_numbers-0.0.3.dist-info/METADATA
fast_prime_numbers-0.0.3.dist-info/WHEEL
fast_prime_numbers-0.0.3.dist-info/top_level.txt
fast_prime_numbers-0.0.3.dist-info/RECORD
