Metadata-Version: 2.1
Name: fast-prime-numbers
Version: 0.0.3
Summary: Fastest Prime Number Calculation (checks) logic for python. Also contains other prime number calculation ways
Home-page: https://github.com/ganeshkbhat/fastprimecalculations/tree/main/python
Author: Ganesh Bhat
Author-email: Ganesh Bhat <ganeshsurfs@gmail.com>
Project-URL: Homepage, https://github.com/ganeshkbhat/fastprimecalculations
Project-URL: Bug Tracker, https://github.com/ganeshkbhat/fastprimecalculations/issues
Keywords: fast prime numbers primenumber calculations primenumbers
Classifier: Intended Audience :: Developers
Classifier: License :: OSI Approved :: MIT License
Classifier: Programming Language :: Python :: 2
Classifier: Programming Language :: Python :: 2.7
Classifier: Programming Language :: Python :: 3
Classifier: Programming Language :: Python :: 3.5
Classifier: Programming Language :: Python :: 3.6
Classifier: Programming Language :: Python :: 3.7
Classifier: License :: OSI Approved :: MIT License
Classifier: Operating System :: OS Independent
Requires-Python: >=2.7, !=3.0.*, !=3.1.*, !=3.2.*, !=3.3.*, !=3.4.*, <4
License-File: LICENSE
Provides-Extra: dev
Provides-Extra: test
